odoo/addons/crm_lead_dms_api/README.rst
odoo/addons/crm_lead_dms_api/__init__.py
odoo/addons/crm_lead_dms_api/__manifest__.py
odoo/addons/crm_lead_dms_api/models/__init__.py
odoo/addons/crm_lead_dms_api/models/dms_category.py
odoo/addons/crm_lead_dms_api/services/__init__.py
odoo/addons/crm_lead_dms_api/services/crm_lead_service.py
odoo/addons/crm_lead_dms_api/static/description/icon.png
odoo/addons/crm_lead_dms_api/static/description/icon.svg
odoo/addons/crm_lead_dms_api/tests/__init__.py
odoo/addons/crm_lead_dms_api/tests/test_crm_lead_service.py
odoo12_addon_crm_lead_dms_api-12.0.0.1.0.dist-info/METADATA
odoo12_addon_crm_lead_dms_api-12.0.0.1.0.dist-info/WHEEL
odoo12_addon_crm_lead_dms_api-12.0.0.1.0.dist-info/top_level.txt
odoo12_addon_crm_lead_dms_api-12.0.0.1.0.dist-info/RECORD
