Metadata-Version: 2.1
Name: odoo12-addon-crm-lead-dms-api
Version: 12.0.0.1.0
Summary: API to check if a CRM Lead has all the required documents
Home-page: https://gitlab.com/somitcoop/erp-research/odoo-helpdesk
Author: Som It Cooperatiu SCCL, Som Connexió SCCL, Odoo Community Association (OCA)
Author-email: support@odoo-community.org
License: AGPL-3
Platform: UNKNOWN
Classifier: Programming Language :: Python
Classifier: Framework :: Odoo
Classifier: Framework :: Odoo :: 12.0
Classifier: License :: OSI Approved :: GNU Affero General Public License v3
Requires-Python: >=3.5
Requires-Dist: odoo12-addon-api-common-base
Requires-Dist: odoo12-addon-crm-lead-dms-category
Requires-Dist: odoo12-addon-crm-lead-token
Requires-Dist: odoo (<12.1dev,>=12.0a)
